Metadata-Version: 2.1
Name: modulos-image
Version: 0.0.1
Summary: My short description
Home-page: UNKNOWN
Author: MARCIOXANDIR
Author-email: marcioalexdias@gmail.com
License: UNKNOWN
Platform: UNKNOWN
Requires-Python: >=3.8
License-File: LICENCE
